wallgen/Config.py
wallgen/WallGenDBUSService.py
wallgen/__init__.py
wallgen/__main__.py
wallgen/__util__.py
wallgen/from_local.py
wallgen/from_reddit.py
wallgen-0.2.3.data/scripts/wallgen
wallgen-0.2.3.dist-info/LICENSE
wallgen-0.2.3.dist-info/LICENSE.md
wallgen-0.2.3.dist-info/METADATA
wallgen-0.2.3.dist-info/WHEEL
wallgen-0.2.3.dist-info/top_level.txt
wallgen-0.2.3.dist-info/RECORD
