Metadata-Version: 2.1
Name: wallgen
Version: 0.2.3
Summary: A wallpaper generator for gnome (and kde)
Home-page: https://github.com/hobbypunk90/wallgen
Author: Marcel Hoppe
Author-email: hoppe.marcel@gmail.com
License: UNKNOWN
Platform: UNKNOWN
Classifier: Programming Language :: Python :: 3
Classifier: License :: OSI Approved :: MIT License
Classifier: Operating System :: POSIX :: Linux
Classifier: Environment :: X11 Applications :: Gnome
Classifier: Environment :: X11 Applications :: KDE
License-File: LICENSE
License-File: LICENSE.md
